{"state_province_data": [
{"Region":"United States","Country_State_Province":"Alabama","TotalCurrentStudentEnrollment":"915","CurrentPercentFemaleEnrollment":"0.157377049","TotalStudentsSinceInception":"13548","CiscoCertificationsSinceInception":"2059","geometry":{"coordinates": [-86.902298, 32.318231], "type": "Point" }},
{"Region":"United States","Country_State_Province":"Alaska","TotalCurrentStudentEnrollment":"387","CurrentPercentFemaleEnrollment":"0.157622739","TotalStudentsSinceInception":"5458","CiscoCertificationsSinceInception":"1477","geometry":{"coordinates": [-154.493062, 63.588753], "type": "Point" }},
{"Region":"United States","Country_State_Province":"Arizona","TotalCurrentStudentEnrollment":"2751","CurrentPercentFemaleEnrollment":"0.135587059","TotalStudentsSinceInception":"38064","CiscoCertificationsSinceInception":"6818","geometry":{"coordinates": [-111.093731, 34.048928], "type": "Point" }},
{"Region":"United States","Country_State_Province":"Arkansas","TotalCurrentStudentEnrollment":"886","CurrentPercentFemaleEnrollment":"0.125282167","TotalStudentsSinceInception":"19393","CiscoCertificationsSinceInception":"4606","geometry":{"coordinates": [-91.831833, 35.20105], "type": "Point" }},
{"Region":"United States","Country_State_Province":"California","TotalCurrentStudentEnrollment":"20446","CurrentPercentFemaleEnrollment":"0.116599824","TotalStudentsSinceInception":"210891","CiscoCertificationsSinceInception":"38240","geometry":{"coordinates": [-119.417932, 36.778261], "type": "Point" }},
{"Region":"United States","Country_State_Province":"Colorado","TotalCurrentStudentEnrollment":"987","CurrentPercentFemaleEnrollment":"0.152988855","TotalStudentsSinceInception":"23243","CiscoCertificationsSinceInception":"6254","geometry":{"coordinates": [-105.782067, 39.550051], "type": "Point" }},
{"Region":"United States","Country_State_Province":"Connecticut","TotalCurrentStudentEnrollment":"1183","CurrentPercentFemaleEnrollment":"0.140321217","TotalStudentsSinceInception":"9848","CiscoCertificationsSinceInception":"1595","geometry":{"coordinates": [-73.087749, 41.603221], "type": "Point" }},
{"Region":"United States","Country_State_Province":"Delaware","TotalCurrentStudentEnrollment":"506","CurrentPercentFemaleEnrollment":"0.193675889","TotalStudentsSinceInception":"2321","CiscoCertificationsSinceInception":"335","geometry":{"coordinates": [-75.52767, 38.910832], "type": "Point" }},
{"Region":"United States","Country_State_Province":"Florida","TotalCurrentStudentEnrollment":"8580","CurrentPercentFemaleEnrollment":"0.138461538","TotalStudentsSinceInception":"78718","CiscoCertificationsSinceInception":"16041","geometry":{"coordinates": [-81.515754, 27.664827], "type": "Point" }},
{"Region":"United States","Country_State_Province":"Georgia","TotalCurrentStudentEnrollment":"5848","CurrentPercentFemaleEnrollment":"0.172366621","TotalStudentsSinceInception":"69887","CiscoCertificationsSinceInception":"20843","geometry":{"coordinates": [-82.907123, 32.157435], "type": "Point" }},
{"Region":"United States","Country_State_Province":"Hawaii","TotalCurrentStudentEnrollment":"821","CurrentPercentFemaleEnrollment":"0.148599269","TotalStudentsSinceInception":"11237","CiscoCertificationsSinceInception":"2395","geometry":{"coordinates": [-155.665857, 19.898682], "type": "Point" }},
{"Region":"United States","Country_State_Province":"Idaho","TotalCurrentStudentEnrollment":"606","CurrentPercentFemaleEnrollment":"0.113861386","TotalStudentsSinceInception":"8060","CiscoCertificationsSinceInception":"1487","geometry":{"coordinates": [-114.742041, 44.068202], "type": "Point" }},
{"Region":"United States","Country_State_Province":"Illinois","TotalCurrentStudentEnrollment":"6372","CurrentPercentFemaleEnrollment":"0.152542373","TotalStudentsSinceInception":"67161","CiscoCertificationsSinceInception":"17169","geometry":{"coordinates": [-89.398528, 40.633125], "type": "Point" }},
{"Region":"United States","Country_State_Province":"Indiana","TotalCurrentStudentEnrollment":"2733","CurrentPercentFemaleEnrollment":"0.124039517","TotalStudentsSinceInception":"27668","CiscoCertificationsSinceInception":"5649","geometry":{"coordinates": [-85.602364, 40.551217], "type": "Point" }},
{"Region":"United States","Country_State_Province":"Iowa","TotalCurrentStudentEnrollment":"897","CurrentPercentFemaleEnrollment":"0.094760312","TotalStudentsSinceInception":"16565","CiscoCertificationsSinceInception":"2948","geometry":{"coordinates": [-93.097702, 41.878003], "type": "Point" }},
{"Region":"United States","Country_State_Province":"Kansas","TotalCurrentStudentEnrollment":"1590","CurrentPercentFemaleEnrollment":"0.13081761","TotalStudentsSinceInception":"20887","CiscoCertificationsSinceInception":"3970","geometry":{"coordinates": [-98.484246, 39.011902], "type": "Point" }},
{"Region":"United States","Country_State_Province":"Kentucky","TotalCurrentStudentEnrollment":"1150","CurrentPercentFemaleEnrollment":"0.125217391","TotalStudentsSinceInception":"25507","CiscoCertificationsSinceInception":"3853","geometry":{"coordinates": [-84.270018, 37.839333], "type": "Point" }},
{"Region":"United States","Country_State_Province":"Louisiana","TotalCurrentStudentEnrollment":"638","CurrentPercentFemaleEnrollment":"0.123824451","TotalStudentsSinceInception":"9761","CiscoCertificationsSinceInception":"1857","geometry":{"coordinates": [-92.145024, 31.244823], "type": "Point" }},
{"Region":"United States","Country_State_Province":"Maine","TotalCurrentStudentEnrollment":"227","CurrentPercentFemaleEnrollment":"0.123348018","TotalStudentsSinceInception":"2471","CiscoCertificationsSinceInception":"349","geometry":{"coordinates": [-69.445469, 45.253783], "type": "Point" }},
{"Region":"United States","Country_State_Province":"Maryland","TotalCurrentStudentEnrollment":"5121","CurrentPercentFemaleEnrollment":"0.191173599","TotalStudentsSinceInception":"31147","CiscoCertificationsSinceInception":"7391","geometry":{"coordinates": [-76.641271, 39.045755], "type": "Point" }},
{"Region":"United States","Country_State_Province":"Massachusetts","TotalCurrentStudentEnrollment":"3015","CurrentPercentFemaleEnrollment":"0.155887231","TotalStudentsSinceInception":"21731","CiscoCertificationsSinceInception":"2875","geometry":{"coordinates": [-71.382437, 42.407211], "type": "Point" }},
{"Region":"United States","Country_State_Province":"Michigan","TotalCurrentStudentEnrollment":"3264","CurrentPercentFemaleEnrollment":"0.122855392","TotalStudentsSinceInception":"32400","CiscoCertificationsSinceInception":"7788","geometry":{"coordinates": [-85.602364, 44.314844], "type": "Point" }},
{"Region":"United States","Country_State_Province":"Minnesota","TotalCurrentStudentEnrollment":"2478","CurrentPercentFemaleEnrollment":"0.129539952","TotalStudentsSinceInception":"33178","CiscoCertificationsSinceInception":"6436","geometry":{"coordinates": [-94.6859, 46.729553], "type": "Point" }},
{"Region":"United States","Country_State_Province":"Mississippi","TotalCurrentStudentEnrollment":"565","CurrentPercentFemaleEnrollment":"0.139823009","TotalStudentsSinceInception":"9421","CiscoCertificationsSinceInception":"2108","geometry":{"coordinates": [-89.398528, 32.354668], "type": "Point" }},
{"Region":"United States","Country_State_Province":"Missouri","TotalCurrentStudentEnrollment":"3190","CurrentPercentFemaleEnrollment":"0.146081505","TotalStudentsSinceInception":"28854","CiscoCertificationsSinceInception":"6715","geometry":{"coordinates": [-91.831833, 37.964253], "type": "Point" }},
{"Region":"United States","Country_State_Province":"Montana","TotalCurrentStudentEnrollment":"350","CurrentPercentFemaleEnrollment":"0.122857143","TotalStudentsSinceInception":"7953","CiscoCertificationsSinceInception":"1986","geometry":{"coordinates": [-110.362566, 46.879682], "type": "Point" }},
{"Region":"United States","Country_State_Province":"Nebraska","TotalCurrentStudentEnrollment":"703","CurrentPercentFemaleEnrollment":"0.099573257","TotalStudentsSinceInception":"11144","CiscoCertificationsSinceInception":"3020","geometry":{"coordinates": [-99.901813, 41.492537], "type": "Point" }},
{"Region":"United States","Country_State_Province":"Nevada","TotalCurrentStudentEnrollment":"1219","CurrentPercentFemaleEnrollment":"0.151763741","TotalStudentsSinceInception":"12652","CiscoCertificationsSinceInception":"1893","geometry":{"coordinates": [-116.419389, 38.80261], "type": "Point" }},
{"Region":"United States","Country_State_Province":"New Hampshire","TotalCurrentStudentEnrollment":"870","CurrentPercentFemaleEnrollment":"0.101149425","TotalStudentsSinceInception":"9685","CiscoCertificationsSinceInception":"2632","geometry":{"coordinates": [-71.572395, 43.193852], "type": "Point" }},
{"Region":"United States","Country_State_Province":"New Jersey","TotalCurrentStudentEnrollment":"3363","CurrentPercentFemaleEnrollment":"0.169194172","TotalStudentsSinceInception":"28870","CiscoCertificationsSinceInception":"7238","geometry":{"coordinates": [-74.405661, 40.058324], "type": "Point" }},
{"Region":"United States","Country_State_Province":"New Mexico","TotalCurrentStudentEnrollment":"716","CurrentPercentFemaleEnrollment":"0.162011173","TotalStudentsSinceInception":"7162","CiscoCertificationsSinceInception":"1644","geometry":{"coordinates": [-105.032363, 34.97273], "type": "Point" }},
{"Region":"United States","Country_State_Province":"New York","TotalCurrentStudentEnrollment":"7805","CurrentPercentFemaleEnrollment":"0.152210122","TotalStudentsSinceInception":"79102","CiscoCertificationsSinceInception":"17085","geometry":{"coordinates": [-74.217933, 43.299428], "type": "Point" }},
{"Region":"United States","Country_State_Province":"North Carolina","TotalCurrentStudentEnrollment":"6686","CurrentPercentFemaleEnrollment":"0.168710739","TotalStudentsSinceInception":"67631","CiscoCertificationsSinceInception":"13438","geometry":{"coordinates": [-79.0193, 35.759573], "type": "Point" }},
{"Region":"United States","Country_State_Province":"North Dakota","TotalCurrentStudentEnrollment":"654","CurrentPercentFemaleEnrollment":"0.111620795","TotalStudentsSinceInception":"9921","CiscoCertificationsSinceInception":"1484","geometry":{"coordinates": [-101.002012, 47.551493], "type": "Point" }},
{"Region":"United States","Country_State_Province":"Ohio","TotalCurrentStudentEnrollment":"3963","CurrentPercentFemaleEnrollment":"0.10673732","TotalStudentsSinceInception":"46276","CiscoCertificationsSinceInception":"12694","geometry":{"coordinates": [-82.907123, 40.417287], "type": "Point" }},
{"Region":"United States","Country_State_Province":"Oklahoma","TotalCurrentStudentEnrollment":"1131","CurrentPercentFemaleEnrollment":"0.134394341","TotalStudentsSinceInception":"17072","CiscoCertificationsSinceInception":"3348","geometry":{"coordinates": [-97.092877, 35.007752], "type": "Point" }},
{"Region":"United States","Country_State_Province":"Oregon","TotalCurrentStudentEnrollment":"827","CurrentPercentFemaleEnrollment":"0.102781137","TotalStudentsSinceInception":"12286","CiscoCertificationsSinceInception":"2969","geometry":{"coordinates": [-120.554201, 43.804133], "type": "Point" }},
{"Region":"United States","Country_State_Province":"Pennsylvania","TotalCurrentStudentEnrollment":"3531","CurrentPercentFemaleEnrollment":"0.108467856","TotalStudentsSinceInception":"38310","CiscoCertificationsSinceInception":"6951","geometry":{"coordinates": [-77.194525, 41.203322], "type": "Point" }},
{"Region":"United States","Country_State_Province":"Rhode Island","TotalCurrentStudentEnrollment":"605","CurrentPercentFemaleEnrollment":"0.109090909","TotalStudentsSinceInception":"8114","CiscoCertificationsSinceInception":"1796","geometry":{"coordinates": [-71.477429, 41.580095], "type": "Point" }},
{"Region":"United States","Country_State_Province":"South Carolina","TotalCurrentStudentEnrollment":"1432","CurrentPercentFemaleEnrollment":"0.127094972","TotalStudentsSinceInception":"16810","CiscoCertificationsSinceInception":"3244","geometry":{"coordinates": [-81.163725, 33.836081], "type": "Point" }},
{"Region":"United States","Country_State_Province":"South Dakota","TotalCurrentStudentEnrollment":"312","CurrentPercentFemaleEnrollment":"0.073717949","TotalStudentsSinceInception":"6994","CiscoCertificationsSinceInception":"1354","geometry":{"coordinates": [-99.901813, 43.969515], "type": "Point" }},
{"Region":"United States","Country_State_Province":"Tennessee","TotalCurrentStudentEnrollment":"1486","CurrentPercentFemaleEnrollment":"0.152759085","TotalStudentsSinceInception":"11073","CiscoCertificationsSinceInception":"1804","geometry":{"coordinates": [-86.580447, 35.517491], "type": "Point" }},
{"Region":"United States","Country_State_Province":"Texas","TotalCurrentStudentEnrollment":"11274","CurrentPercentFemaleEnrollment":"0.124623026","TotalStudentsSinceInception":"127437","CiscoCertificationsSinceInception":"29373","geometry":{"coordinates": [-99.901813, 31.968599], "type": "Point" }},
{"Region":"United States","Country_State_Province":"Utah","TotalCurrentStudentEnrollment":"1050","CurrentPercentFemaleEnrollment":"0.086666667","TotalStudentsSinceInception":"8115","CiscoCertificationsSinceInception":"1130","geometry":{"coordinates": [-111.093731, 39.32098], "type": "Point" }},
{"Region":"United States","Country_State_Province":"Vermont","TotalCurrentStudentEnrollment":"231","CurrentPercentFemaleEnrollment":"0.12987013","TotalStudentsSinceInception":"2912","CiscoCertificationsSinceInception":"425","geometry":{"coordinates": [-72.577841, 44.558803], "type": "Point" }},
{"Region":"United States","Country_State_Province":"Virginia","TotalCurrentStudentEnrollment":"5185","CurrentPercentFemaleEnrollment":"0.154098361","TotalStudentsSinceInception":"47109","CiscoCertificationsSinceInception":"10869","geometry":{"coordinates": [-78.656894, 37.431573], "type": "Point" }},
{"Region":"United States","Country_State_Province":"Washington","TotalCurrentStudentEnrollment":"3228","CurrentPercentFemaleEnrollment":"0.131660471","TotalStudentsSinceInception":"36928","CiscoCertificationsSinceInception":"9559","geometry":{"coordinates": [-120.740139, 47.751074], "type": "Point" }},
{"Region":"United States","Country_State_Province":"Washington, D.C.","TotalCurrentStudentEnrollment":"343","CurrentPercentFemaleEnrollment":"0.346938776","TotalStudentsSinceInception":"2814","CiscoCertificationsSinceInception":"76","geometry":{"coordinates": [-77.033418, 38.905985], "type": "Point" }},
{"Region":"United States","Country_State_Province":"West Virginia","TotalCurrentStudentEnrollment":"545","CurrentPercentFemaleEnrollment":"0.082568807","TotalStudentsSinceInception":"11148","CiscoCertificationsSinceInception":"3343","geometry":{"coordinates": [-80.454903, 38.597626], "type": "Point" }},
{"Region":"United States","Country_State_Province":"Wisconsin","TotalCurrentStudentEnrollment":"3234","CurrentPercentFemaleEnrollment":"0.106369821","TotalStudentsSinceInception":"34796","CiscoCertificationsSinceInception":"7675","geometry":{"coordinates": [-88.787868, 43.78444], "type": "Point" }},
{"Region":"United States","Country_State_Province":"Wyoming","TotalCurrentStudentEnrollment":"198","CurrentPercentFemaleEnrollment":"0.106060606","TotalStudentsSinceInception":"3658","CiscoCertificationsSinceInception":"800","geometry":{"coordinates": [-107.290284, 43.075968], "type": "Point" }},
{"Region":"Canada","Country_State_Province":"Alberta","TotalCurrentStudentEnrollment":"1523","CurrentPercentFemaleEnrollment":"0.09980302","TotalStudentsSinceInception":"12450","CiscoCertificationsSinceInception":"3046","geometry":{"coordinates": [-116.576504, 53.933271], "type": "Point" }},
{"Region":"Canada","Country_State_Province":"British Columbia","TotalCurrentStudentEnrollment":"2008","CurrentPercentFemaleEnrollment":"0.139940239","TotalStudentsSinceInception":"17728","CiscoCertificationsSinceInception":"4388","geometry":{"coordinates": [-127.647621, 53.726668], "type": "Point" }},
{"Region":"Canada","Country_State_Province":"Manitoba","TotalCurrentStudentEnrollment":"1279","CurrentPercentFemaleEnrollment":"0.107114934","TotalStudentsSinceInception":"9331","CiscoCertificationsSinceInception":"2060","geometry":{"coordinates": [-98.813876, 53.760861], "type": "Point" }},
{"Region":"Canada","Country_State_Province":"New Brunswick","TotalCurrentStudentEnrollment":"379","CurrentPercentFemaleEnrollment":"0.071240106","TotalStudentsSinceInception":"4581","CiscoCertificationsSinceInception":"662","geometry":{"coordinates": [-66.461916, 46.565316], "type": "Point" }},
{"Region":"Canada","Country_State_Province":"Newfoundland and Labrador","TotalCurrentStudentEnrollment":"260","CurrentPercentFemaleEnrollment":"0.157692308","TotalStudentsSinceInception":"1634","CiscoCertificationsSinceInception":"392","geometry":{"coordinates": [-57.660436, 53.135509], "type": "Point" }},
{"Region":"Canada","Country_State_Province":"Nova Scotia","TotalCurrentStudentEnrollment":"312","CurrentPercentFemaleEnrollment":"0.102564103","TotalStudentsSinceInception":"4697","CiscoCertificationsSinceInception":"742","geometry":{"coordinates": [-63.744311, 44.681987], "type": "Point" }},
{"Region":"Canada","Country_State_Province":"Northwest Territories","TotalCurrentStudentEnrollment":"5","CurrentPercentFemaleEnrollment":"0","TotalStudentsSinceInception":"13","CiscoCertificationsSinceInception":"","geometry":{"coordinates": [-124.845733, 64.825544], "type": "Point" }},
{"Region":"Canada","Country_State_Province":"Nunavut","TotalCurrentStudentEnrollment":"5","CurrentPercentFemaleEnrollment":"0","TotalStudentsSinceInception":"23","CiscoCertificationsSinceInception":"","geometry":{"coordinates": [-83.107577, 70.299771], "type": "Point" }},
{"Region":"Canada","Country_State_Province":"Ontario","TotalCurrentStudentEnrollment":"10138","CurrentPercentFemaleEnrollment":"0.143815348","TotalStudentsSinceInception":"76125","CiscoCertificationsSinceInception":"16769","geometry":{"coordinates": [-85.323214, 51.253775], "type": "Point" }},
{"Region":"Canada","Country_State_Province":"Prince Edward Island","TotalCurrentStudentEnrollment":"83","CurrentPercentFemaleEnrollment":"0.048192771","TotalStudentsSinceInception":"816","CiscoCertificationsSinceInception":"256","geometry":{"coordinates": [-63.416814, 46.510712], "type": "Point" }},
{"Region":"Canada","Country_State_Province":"Quebec","TotalCurrentStudentEnrollment":"5045","CurrentPercentFemaleEnrollment":"0.093756194","TotalStudentsSinceInception":"41213","CiscoCertificationsSinceInception":"11785","geometry":{"coordinates": [-71.207981, 46.813878], "type": "Point" }},
{"Region":"Canada","Country_State_Province":"Saskatchewan","TotalCurrentStudentEnrollment":"241","CurrentPercentFemaleEnrollment":"0.199170124","TotalStudentsSinceInception":"3964","CiscoCertificationsSinceInception":"549","geometry":{"coordinates": [-106.450864, 52.939916], "type": "Point" }},
{"Region":"Canada","Country_State_Province":"Yukon","TotalCurrentStudentEnrollment":"1","CurrentPercentFemaleEnrollment":"0","TotalStudentsSinceInception":"1","CiscoCertificationsSinceInception":"","geometry":{"coordinates": [-135.000000, 64.282327], "type": "Point" }}
]}